{
  "POIs": [
    {
      "fit": [
        0.0,
        0.04263312369585037,
        0.14013320207595825
      ],
      "name": "r"
    }
  ],
  "method": "default",
  "params": [
    {
      "fit": [
        218761.109375,
        219225.78125,
        219690.484375
      ],
      "groups": [],
      "impact_r": 0.0001660361886024475,
      "name": "Background_fail_LOW_bin_1-1",
      "prefit": [
        219243.0,
        219243.0,
        219243.0
      ],
      "r": [
        0.04271263629198074,
        0.04263312369585037,
        0.04279915988445282
      ],
      "type": "Unconstrained"
    },
    {
      "fit": [
        20372.517578125,
        20505.763671875,
        20639.544921875
      ],
      "groups": [],
      "impact_r": 0.0001080147922039032,
      "name": "Background_fail_LOW_bin_2-1",
      "prefit": [
        20514.0,
        20514.0,
        20514.0
      ],
      "r": [
        0.042725820094347,
        0.04263312369585037,
        0.042741138488054276
      ],
      "type": "Unconstrained"
    },
    {
      "fit": [
        3493.93896484375,
        3548.8896484375,
        3604.397705078125
      ],
      "groups": [],
      "impact_r": 1.8864870071411133e-05,
      "name": "Background_fail_LOW_bin_3-1",
      "prefit": [
        3530.0,
        3530.0,
        3530.0
      ],
      "r": [
        0.04262980818748474,
        0.04263312369585037,
        0.04261425882577896
      ],
      "type": "Unconstrained"
    },
    {
      "fit": [
        854.653564453125,
        881.8602905273438,
        909.6469116210938
      ],
      "groups": [],
      "impact_r": 4.428252577781677e-05,
      "name": "Background_fail_LOW_bin_4-1",
      "prefit": [
        867.0,
        867.0,
        867.0
      ],
      "r": [
        0.04266062751412392,
        0.04263312369585037,
        0.042588841170072556
      ],
      "type": "Unconstrained"
    },
    {
      "fit": [
        219.2447509765625,
        233.09754943847656,
        247.51531982421875
      ],
      "groups": [],
      "impact_r": 0.00010109320282936096,
      "name": "Background_fail_LOW_bin_5-1",
      "prefit": [
        235.0,
        235.0,
        235.0
      ],
      "r": [
        0.04272545501589775,
        0.04263312369585037,
        0.04253203049302101
      ],
      "type": "Unconstrained"
    },
    {
      "fit": [
        68.45989990234375,
        76.26606750488281,
        84.63892364501953
      ],
      "groups": [],
      "impact_r": 0.00015785172581672668,
      "name": "Background_fail_SIG_bin_1-1",
      "prefit": [
        81.0,
        81.0,
        81.0
      ],
      "r": [
        0.0427909754216671,
        0.04263312369585037,
        0.04252971336245537
      ],
      "type": "Unconstrained"
    },
    {
      "fit": [
        13.569622039794922,
        17.121227264404297,
        21.248292922973633
      ],
      "groups": [],
      "impact_r": 0.0005615167319774628,
      "name": "Background_fail_SIG_bin_2-1",
      "prefit": [
        17.0,
        17.0,
        17.0
      ],
      "r": [
        0.043194640427827835,
        0.04263312369585037,
        0.04231895133852959
      ],
      "type": "Unconstrained"
    },
    {
      "fit": [
        6.127723693847656,
        8.563926696777344,
        11.563944816589355
      ],
      "groups": [],
      "impact_r": 0.0006654933094978333,
      "name": "Background_fail_SIG_bin_3-1",
      "prefit": [
        10.0,
        10.0,
        10.0
      ],
      "r": [
        0.043298617005348206,
        0.04263312369585037,
        0.04251402989029884
      ],
      "type": "Unconstrained"
    },
    {
      "fit": [
        0.8326510190963745,
        1.9609814882278442,
        3.7559916973114014
      ],
      "groups": [],
      "impact_r": 0.021814551204442978,
      "name": "Background_fail_SIG_bin_4-1",
      "prefit": [
        5.0,
        5.0,
        5.0
      ],
      "r": [
        0.06174459680914879,
        0.04263312369585037,
        0.020818572491407394
      ],
      "type": "Unconstrained"
    },
    {
      "fit": [
        1.6595388650894165,
        1.6684436798095703,
        1.6773890256881714
      ],
      "groups": [],
      "impact_r": 0.00026374682784080505,
      "name": "Background_rpf_0x0_par0",
      "prefit": [
        0.1,
        0.1,
        0.1
      ],
      "r": [
        0.04289687052369118,
        0.04263312369585037,
        0.04263748601078987
      ],
      "type": "Unconstrained"
    },
    {
      "fit": [
        -1.0002521276474,
        0.00047391711268574,
        1.0002540349960327
      ],
      "groups": [],
      "impact_r": 0.0007635466754436493,
      "name": "lumi",
      "prefit": [
        -0.9999999999999999,
        0.0,
        0.9999999999999999
      ],
      "r": [
        0.04330846294760704,
        0.04254491627216339,
        0.04196507856249809
      ],
      "type": "Gaussian"
    },
    {
      "fit": [
        -0.9998732805252075,
        0.000455617846455425,
        1.000662088394165
      ],
      "groups": [],
      "impact_r": 0.00014958158135414124,
      "name": "pileup",
      "prefit": [
        -0.9999999999999999,
        0.0,
        0.9999999999999999
      ],
      "r": [
        0.04254349321126938,
        0.04269307479262352,
        0.04270797222852707
      ],
      "type": "Gaussian"
    },
    {
      "fit": [
        -1.000172734260559,
        0.00013404348283074796,
        1.0002533197402954
      ],
      "groups": [],
      "impact_r": 0.000214453786611557,
      "name": "systOnF",
      "prefit": [
        -0.9999999999999999,
        0.0,
        0.9999999999999999
      ],
      "r": [
        0.04283979907631874,
        0.042625345289707184,
        0.042419303208589554
      ],
      "type": "Gaussian"
    },
    {
      "fit": [
        -0.9976102709770203,
        -0.00016135605983436108,
        1.0004611015319824
      ],
      "groups": [],
      "impact_r": 0.0019725821912288666,
      "name": "systOnG",
      "prefit": [
        -0.9999999999999999,
        0.0,
        0.9999999999999999
      ],
      "r": [
        0.04255900904536247,
        0.04271335154771805,
        0.044685933738946915
      ],
      "type": "Gaussian"
    },
    {
      "fit": [
        -1.0002505779266357,
        5.792764113721205e-06,
        1.0002617835998535
      ],
      "groups": [],
      "impact_r": 8.977949619293213e-06,
      "name": "systOnMuID",
      "prefit": [
        -0.9999999999999999,
        0.0,
        0.9999999999999999
      ],
      "r": [
        0.04262416064739227,
        0.042633138597011566,
        0.042624302208423615
      ],
      "type": "Gaussian"
    },
    {
      "fit": [
        -1.0002501010894775,
        2.265337343487772e-06,
        1.000254511833191
      ],
      "groups": [],
      "impact_r": 8.93324613571167e-06,
      "name": "systOnMuReco",
      "prefit": [
        -0.9999999999999999,
        0.0,
        0.9999999999999999
      ],
      "r": [
        0.042624328285455704,
        0.042633142322301865,
        0.04262420907616615
      ],
      "type": "Gaussian"
    },
    {
      "fit": [
        -1.000252604484558,
        -5.858227609678579e-07,
        1.0002516508102417
      ],
      "groups": [],
      "impact_r": 8.769333362579346e-06,
      "name": "systOnMuTrigger",
      "prefit": [
        -0.9999999999999999,
        0.0,
        0.9999999999999999
      ],
      "r": [
        0.04262440651655197,
        0.04263317584991455,
        0.04262463375926018
      ],
      "type": "Gaussian"
    },
    {
      "fit": [
        -1.000240683555603,
        0.00019726139726117253,
        1.000206470489502
      ],
      "groups": [],
      "impact_r": 7.842108607292175e-05,
      "name": "systOnPt",
      "prefit": [
        -0.9999999999999999,
        0.0,
        0.9999999999999999
      ],
      "r": [
        0.042630963027477264,
        0.042649753391742706,
        0.04272817447781563
      ],
      "type": "Gaussian"
    },
    {
      "fit": [
        -0.9968039989471436,
        0.004038287792354822,
        1.002936840057373
      ],
      "groups": [],
      "impact_r": 0.01631660759449005,
      "name": "systOnTrigger",
      "prefit": [
        -0.9999999999999999,
        0.0,
        0.9999999999999999
      ],
      "r": [
        0.05900581553578377,
        0.042689207941293716,
        0.03330070152878761
      ],
      "type": "Gaussian"
    }
  ]
}